carnot/__init__.py
carnot/reversible.py
carnot/transaction.py
carnot-0.1.1.dist-info/WHEEL
carnot-0.1.1.dist-info/METADATA
carnot-0.1.1.dist-info/RECORD
