Metadata-Version: 2.1
Name: carnot
Version: 0.1.1
Summary: Module for defining reversible transactions.
Home-page: https://jjj999.github.io/carnot
License: MIT
Author: jjj999
Author-email: jjj999to@gmail.com
Maintainer: jjj999
Maintainer-email: jjj999to@gmail.com
Requires-Python: >=3.8,<4.0
Classifier: License :: OSI Approved :: MIT License
Classifier: Programming Language :: Python :: 3
Classifier: Programming Language :: Python :: 3.10
Classifier: Programming Language :: Python :: 3.8
Classifier: Programming Language :: Python :: 3.9
Requires-Dist: typing-extensions (>=4.3.0,<5.0.0)
Project-URL: Repository, https://github.com/jjj999/carnot
